PLP_Output
