Metadata-Version: 1.1
Name: PLP-Output
Version: 0.0.6
Summary: Libreria para tratamiento de salidas PLP
Home-page: https://github.com/javierclb/PLP-Output
Author: Javier De la Fuente Arce
Author-email: javier.delafuente18@outlook.com
License: MIT
Download-URL: https://github.com/javierclb/PLP-Output/tree/master/dist
Keywords: PLP,energy,CDEC
Platform: UNKNOWN
